MANIFEST.in
README.rst
setup.cfg
setup.py
tgext/__init__.py
tgext.socketio.egg-info/PKG-INFO
tgext.socketio.egg-info/SOURCES.txt
tgext.socketio.egg-info/dependency_links.txt
tgext.socketio.egg-info/entry_points.txt
tgext.socketio.egg-info/namespace_packages.txt
tgext.socketio.egg-info/not-zip-safe
tgext.socketio.egg-info/requires.txt
tgext.socketio.egg-info/top_level.txt
tgext/socketio/__init__.py
tgext/socketio/controller.py
tgext/socketio/namespace.py
tgext/socketio/pubsub.py
tgext/socketio/server.py