Metadata-Version: 1.0
Name: tgext.socketio
Version: 0.0.1
Summary: SocketIO support for TurboGears through gevent-socketio
Home-page: http://github.com/amol-/tgext.socketio
Author: Alessandro Molina
Author-email: alessandro.molina@axant.it
License: MIT
Keywords: turbogears2.extension,socketio,gevent
Platform: UNKNOWN
